<annotation>
<folder>json</folder>
<filename>_DSC4168_4HmzE6717J.jpg</filename>
<source>
	<database>Unknown</database>
</source>
<size>
	<width>512</width>
	<height>512</height>
	<depth>Unspecified</depth>
</size>
<segmented>Unspecified</segmented>
<object>
	<name>Fallopia-Convolvulus-poly</name>
	<pose>Unspecified</pose>
	<truncated>Unspecified</truncated>
	<difficult>Unspecified</difficult>
	<occluded>Unspecified</occluded>
	<bndbox>
		<xmin>167</xmin>
		<xmax>257</xmax>
		<ymin>61</ymin>
		<ymax>134</ymax>
	</bndbox>
</object>
<object>
	<name>Wheat-grain-damaged-poly</name>
	<pose>Unspecified</pose>
	<truncated>Unspecified</truncated>
	<difficult>Unspecified</difficult>
	<occluded>Unspecified</occluded>
	<bndbox>
		<xmin>0</xmin>
		<xmax>78</xmax>
		<ymin>274</ymin>
		<ymax>369</ymax>
	</bndbox>
</object>
</annotation>