<annotation>
<folder>json</folder>
<filename>_DSC4168_Q886MuVE5B.jpg</filename>
<source>
	<database>Unknown</database>
</source>
<size>
	<width>512</width>
	<height>512</height>
	<depth>Unspecified</depth>
</size>
<segmented>Unspecified</segmented>
<object>
	<name>Agrostemma-poly</name>
	<pose>Unspecified</pose>
	<truncated>Unspecified</truncated>
	<difficult>Unspecified</difficult>
	<occluded>Unspecified</occluded>
	<bndbox>
		<xmin>226</xmin>
		<xmax>335</xmax>
		<ymin>432</ymin>
		<ymax>511</ymax>
	</bndbox>
</object>
<object>
	<name>Fallopia-Convolvulus-poly</name>
	<pose>Unspecified</pose>
	<truncated>Unspecified</truncated>
	<difficult>Unspecified</difficult>
	<occluded>Unspecified</occluded>
	<bndbox>
		<xmin>325</xmin>
		<xmax>379</xmax>
		<ymin>432</ymin>
		<ymax>492</ymax>
	</bndbox>
</object>
</annotation>